topdesign/Model_cls.py
topdesign/System_cls.py
topdesign/Utilities_cls.py
topdesign/__init__.py
topdesign/examples/multi_language_model_integration/main_multi_language_models.py
topdesign/examples/multi_language_model_integration/sub_models/constraint_func1.jl
topdesign/examples/multi_language_model_integration/sub_models/constraint_func2.m
topdesign/examples/multi_language_model_integration/sub_models/obj_func.exe
topdesign/examples/multi_language_model_integration/sub_models/obj_func_fortran.f90
topdesign/examples/wf_optimization/PRNG_state.pkl
topdesign/examples/wf_optimization/wf_opt_example-RS.py
topdesign/examples/wf_optimization/inputs/gch.yaml
topdesign/optimizer/PSO_cls.py
topdesign/optimizer/RCGA_cls.py
topdesign/optimizer/RS_cls.py
topdesign/optimizer/__init__.py
topdesign/wind/Wind_cls.py
topdesign/wind/__init__.py
topdesign/wind_farm/WFEvalSystem_cls.py
topdesign/wind_farm/WFModel_cls.py
topdesign/wind_farm/__init__.py
topdesign-0.0.3.1.dist-info/METADATA
topdesign-0.0.3.1.dist-info/WHEEL
topdesign-0.0.3.1.dist-info/licenses/LICENSE
topdesign-0.0.3.1.dist-info/RECORD
