Metadata-Version: 2.4
Name: topdesign
Version: 0.0.3.1
Summary: A general tool chain integration framework for multidisciplinary analysis and optimization
Author-email: Ju Feng <jufen@dtu.dk>
License-File: LICENSE
Classifier: License :: OSI Approved :: MIT License
Classifier: Operating System :: OS Independent
Classifier: Programming Language :: Python :: 3
Requires-Python: >=3.8
Requires-Dist: matplotlib
Requires-Dist: numpy
Requires-Dist: scipy
